wanting/__init__.py
wanting/py.typed
wanting/wanting.py
wanting-0.13.0.dist-info/licenses/LICENSE
wanting-0.13.0.dist-info/METADATA
wanting-0.13.0.dist-info/WHEEL
wanting-0.13.0.dist-info/top_level.txt
wanting-0.13.0.dist-info/RECORD
