Metadata-Version: 2.4
Name: wanting
Version: 0.13.0
Summary: A library for creating, and working with models that can represent incomplete information.
Author-email: Narvin Singh <Narvin.A.Singh@gmail.com>
License: Wanting is a library for working with incomplete models.
Project-URL: Homepage, https://gitlab.com/narvin/wanting
Project-URL: Repository, https://gitlab.com/narvin/wanting
Project-URL: Bug Tracker, https://gitlab.com/narvin/wanting/-/issues
Classifier: Programming Language :: Python :: 3
Classifier: License :: OSI Approved :: GNU General Public License v3 or later (GPLv3+)
Classifier: Operating System :: OS Independent
Requires-Python: >=3.12
License-File: LICENSE
Requires-Dist: pydantic~=2.11
Provides-Extra: dev
Requires-Dist: mypy~=1.18; extra == "dev"
Requires-Dist: pre-commit~=4.3; extra == "dev"
Requires-Dist: pytest~=8.4; extra == "dev"
Requires-Dist: ruff~=0.14.2; extra == "dev"
Requires-Dist: yamllint~=1.37; extra == "dev"
Provides-Extra: doc
Requires-Dist: python-docs-theme~=2025.10; extra == "doc"
Requires-Dist: sphinx~=8.2; extra == "doc"
Provides-Extra: deploy
Requires-Dist: build~=1.3; extra == "deploy"
Requires-Dist: twine~=6.2; extra == "deploy"
Dynamic: license-file
